odoo8_addon_l10n_br_account_product_service-8.0.2.0.0-py2.7-nspkg.pth
odoo8_addon_l10n_br_account_product_service-8.0.2.0.0.dist-info/top_level.txt
odoo8_addon_l10n_br_account_product_service-8.0.2.0.0.dist-info/WHEEL
odoo8_addon_l10n_br_account_product_service-8.0.2.0.0.dist-info/RECORD
odoo8_addon_l10n_br_account_product_service-8.0.2.0.0.dist-info/metadata.json
odoo8_addon_l10n_br_account_product_service-8.0.2.0.0.dist-info/DESCRIPTION.rst
odoo8_addon_l10n_br_account_product_service-8.0.2.0.0.dist-info/METADATA
odoo8_addon_l10n_br_account_product_service-8.0.2.0.0.dist-info/namespace_packages.txt
odoo_addons/l10n_br_account_product_service/__openerp__.py
odoo_addons/l10n_br_account_product_service/__init__.py
odoo_addons/l10n_br_account_product_service/README.rst
odoo_addons/l10n_br_account_product_service/models/product.py
odoo_addons/l10n_br_account_product_service/models/res_partner.py
odoo_addons/l10n_br_account_product_service/models/account_invoice.py
odoo_addons/l10n_br_account_product_service/models/__init__.py
odoo_addons/l10n_br_account_product_service/models/l10n_br_account_product_service.py
odoo_addons/l10n_br_account_product_service/i18n/pt_BR.po
